heatmap4kmers/__init__.py
heatmap4kmers/general_heatmap.py
heatmap4kmers/kmers_heatmap.py
heatmap4kmers-1.1.4.dist-info/LICENSE
heatmap4kmers-1.1.4.dist-info/METADATA
heatmap4kmers-1.1.4.dist-info/WHEEL
heatmap4kmers-1.1.4.dist-info/top_level.txt
heatmap4kmers-1.1.4.dist-info/RECORD
