Metadata-Version: 2.1
Name: heatmap4kmers
Version: 1.1.4
Summary: Visualization package dedicated to kmeRs similarity score matrix
Home-page: https://github.com/RafalUrniaz/HeatMap4kmeRs
Author: Rafal Urniaz
License: UNKNOWN
Platform: UNKNOWN
Classifier: Programming Language :: Python :: 3
Classifier: License :: OSI Approved :: MIT License
Classifier: Operating System :: OS Independent
